napari_dab_cellcount/__init__.py
napari_dab_cellcount/_dock_widget.py
napari_dab_cellcount/_model.py
napari_dab_cellcount/_pred.py
napari_dab_cellcount/_utils.py
napari_dab_cellcount/napari.yaml
napari_dab_cellcount-0.1.4.dist-info/LICENSE
napari_dab_cellcount-0.1.4.dist-info/METADATA
napari_dab_cellcount-0.1.4.dist-info/WHEEL
napari_dab_cellcount-0.1.4.dist-info/entry_points.txt
napari_dab_cellcount-0.1.4.dist-info/top_level.txt
napari_dab_cellcount-0.1.4.dist-info/RECORD
